ccd2iso/__init__.py
ccd2iso/__main__.py
ccd2iso/ccd2iso.py
ccd2iso/clonecd.py
ccd2iso-0.0.1.dist-info/LICENSE
ccd2iso-0.0.1.dist-info/METADATA
ccd2iso-0.0.1.dist-info/WHEEL
ccd2iso-0.0.1.dist-info/entry_points.txt
ccd2iso-0.0.1.dist-info/top_level.txt
ccd2iso-0.0.1.dist-info/RECORD
