Metadata-Version: 2.1
Name: ccd2iso
Version: 0.0.1
Summary: Command-line utility to convert a CloneCD .img file to a .iso file
Home-page: https://github.com/jkmartindale/ccd2iso
Author: James Martindale
Author-email: 11380394+jkmartindale@users.noreply.github.com
License: UNKNOWN
Platform: UNKNOWN
Classifier: Environment :: Console
Classifier: License :: OSI Approved :: Mozilla Public License 2.0 (MPL 2.0)
Classifier: Natural Language :: English
Classifier: Operating System :: OS Independent
Classifier: Programming Language :: Python :: 3
Requires-Python: >=3.8
Requires-Dist: progressbar2 (>=3.51)
